<http-page executeResourcesDynamically="false"
    forceEncodingForDynamicResources="false"
    name="/jpetstore/shop/signon.shtml" playRequestsSequentially="false"
    recordedArtifactZipFileName="team/vus/@user@path/%resources%/recorded-artifacts/caae9d2f-fc6b-46ad-9993-d93b1d79b121.zip"
    slaProfileEnabled="false" thinkTime="5715"
    thinkTimeMode="MODE_SIMPLE_THINK_TIME" thinkTimeRangeEnd=""
    thinkTimeRangeStart="" uid="caae9d2f-fc6b-46ad-9993-d93b1d79b121">
    <embedded-action>c6ebcd17-fe1b-4485-b5fc-7c1a627cc909</embedded-action>
    <screenshotFileDescription>recorded-screenshots/sc_75a1cfd4-5b55-49ea-8f0e-984652f22606.jpg</screenshotFileDescription>
</http-page>
<http-action actionType="1" contentType="text/html;charset=ISO-8859-1"
    extractorInjectPathPolicy="2" extractorPathPolicy="1"
    followRedirects="false" generatedByClient="false"
    linkExtractorSeveralMatchOccurrence="1"
    linkExtractorSeveralMatchPolicy="1" linkExtractorType="6"
    method="POST" name="/jpetstore/shop/signon.shtml"
    path="/jpetstore/shop/signon.shtml" postCharset="iso-8859-1"
    postType="1"
    recordedArtifactZipFileName="team/vus/@user@path/%resources%/recorded-artifacts/caae9d2f-fc6b-46ad-9993-d93b1d79b121.zip"
    recordedResponseCode="200"
    refererUid="4839a748-593b-4284-86cc-cfaf55c39563"
    responseSize="6530" serverUid="tri-5cg10762mp"
    slaProfileEnabled="false" uid="c6ebcd17-fe1b-4485-b5fc-7c1a627cc909" useKeepAlive="false">
    <binaryPostContentBase64><![CDATA[dXNlcm5hbWU9ajJlZSZwYXNzd29yZD0ke0F1dG9QYXNzd29yZF82fSZ4PTI4Jnk9NQ==]]></binaryPostContentBase64>
    <responsePageFileDescription>recorded-responses/res_586391a3-b522-41e5-86b1-236cdcd8fb5a.html</responsePageFileDescription>
    <requestContentFileDescription>recorded-requests/req_586391a3-b522-41e5-86b1-236cdcd8fb5a.txt</requestContentFileDescription>
    <parameter encodeName="true" encodeValue="true" name="username"
        recordRawValue="j2ee" separator="=" value="j2ee" valueMode="USE_VALUE"/>
    <parameter encodeName="true" encodeValue="true" name="password"
        recordRawValue="${AutoPassword_6}" separator="="
        value="${AutoPassword_5}" valueMode="USE_VALUE"/>
    <parameter encodeName="true" encodeValue="true" name="x"
        recordRawValue="28" separator="=" value="28" valueMode="USE_VALUE"/>
    <parameter encodeName="true" encodeValue="true" name="y"
        recordRawValue="5" separator="=" value="5" valueMode="USE_VALUE"/>
    <header name="Accept" value="text/html,application/xhtml+xml,application/xml;q=0.9,image/avif,image/webp,image/apng,*/*;q=0.8,application/signed-exchange;v=b3;q=0.7"/>
    <header name="Accept-Encoding" value="gzip, deflate"/>
    <header name="Accept-Language" value="en-US,en;q=0.9"/>
    <header name="Cache-Control" value="max-age=0"/>
    <header name="Content-Type" value="application/x-www-form-urlencoded"/>
    <header name="Cookie" value="JSESSIONID=5AE81A486B195C782F15839445AC5027"/>
    <header name="Host" value="tri-5cg10762mp:8080"/>
    <header name="Origin" value="http://tri-5cg10762mp:8080"/>
    <header name="Proxy-Connection" value="keep-alive"/>
    <header name="Referer" value="http://tri-5cg10762mp:8080/jpetstore/shop/signonForm.shtml"/>
    <header name="Upgrade-Insecure-Requests" value="1"/>
    <header name="User-Agent" value="Mozilla/5.0 (Windows NT 10.0; Win64; x64) AppleWebKit/537.36 (KHTML, like Gecko) Chrome/138.0.0.0 Safari/537.36"/>
    <responseHeaders>HTTP/1.1 200 OK&#xd;
Server: Apache-Coyote/1.1&#xd;
Content-Type: text/html;charset=ISO-8859-1&#xd;
Content-Length: 6530&#xd;
Date: Thu, 07 Aug 2025 10:34:07 GMT</responseHeaders>
    <record-html-infos extractorName="accountBean"
        extractorOccurence="2" extractorRegExp="false" htmlType="2"/>
</http-action>
